monitor_register/__init__.py
monitor_register/api_doc/__init__.py
monitor_register/api_doc/api_doc.py
monitor_register/monitor/__init__.py
monitor_register/monitor/monitor_config.py
monitor_register/util/__init__.py
monitor_register/util/file_util.py
monitor_register-1.0.3.dist-info/METADATA
monitor_register-1.0.3.dist-info/WHEEL
monitor_register-1.0.3.dist-info/top_level.txt
monitor_register-1.0.3.dist-info/RECORD
