Metadata-Version: 2.1
Name: monitor-register
Version: 1.0.3
Summary: Register to monitor server
Home-page: http://git.azure.gagogroup.cn/huangtaihu/python-log-register.git
Author: stsean
Author-email: author@example.com
License: UNKNOWN
Platform: UNKNOWN
Classifier: Programming Language :: Python :: 3.6
Requires-Python: >3.6.0
